pandas_oracle/tools.py
pandas_oracle-1.1.1.dist-info/DESCRIPTION.rst
pandas_oracle-1.1.1.dist-info/METADATA
pandas_oracle-1.1.1.dist-info/RECORD
pandas_oracle-1.1.1.dist-info/WHEEL
pandas_oracle-1.1.1.dist-info/metadata.json
pandas_oracle-1.1.1.dist-info/top_level.txt
