Metadata-Version: 2.0
Name: pandas-oracle
Version: 1.1.1
Summary: Tools for working with an Oracle database from Pandas
Home-page: https://github.com/cwade/pandas_oracle
Author: cwade
Author-email: pysurveyhelper@gmail.com
License: MIT
Keywords: oracle sql query insert insert_multiple pandas dataframe
Platform: UNKNOWN
Classifier: Development Status :: 3 - Alpha
Classifier: Intended Audience :: Developers
Classifier: License :: OSI Approved :: MIT License
Classifier: Programming Language :: Python :: 3
Classifier: Programming Language :: Python :: 3.2
Classifier: Programming Language :: Python :: 3.3
Classifier: Programming Language :: Python :: 3.4
Requires-Dist: cx-Oracle
Requires-Dist: pandas
Requires-Dist: pyaml
